websole/__init__.py
websole/__main__.py
websole/app.py
websole/templates/404.html
websole/templates/console.html
websole/templates/login.html
websole/templates/assets/bootstrap/css/bootstrap.min.css
websole/templates/assets/bootstrap/js/bootstrap.min.js
websole/templates/assets/css/icons.css
websole/templates/assets/css/styles.css
websole/templates/assets/img/illustrations/404.svg
websole/templates/assets/img/illustrations/login.svg
websole/templates/assets/img/illustrations/logo-only.svg
websole/templates/assets/js/console.js
websole/templates/assets/js/script.js
websole-1.0.1.dist-info/LICENSE
websole-1.0.1.dist-info/METADATA
websole-1.0.1.dist-info/WHEEL
websole-1.0.1.dist-info/entry_points.txt
websole-1.0.1.dist-info/top_level.txt
websole-1.0.1.dist-info/RECORD
