Metadata-Version: 2.1
Name: websole
Version: 1.0.1
Summary: A solution to expose command-line tools through web-based console, through docker.
Author-email: jackzzs <jackzzs@outlook.com>
Project-URL: Homepage, https://github.com/jackzzs/websole
Keywords: cli,web,web console
Classifier: Development Status :: 4 - Beta
Classifier: Environment :: Web Environment
Classifier: Intended Audience :: Developers
Classifier: Natural Language :: English
Classifier: License :: OSI Approved :: MIT License
Classifier: Programming Language :: Python :: 3
Classifier: Programming Language :: Python :: 3.8
Classifier: Programming Language :: Python :: 3.9
Classifier: Programming Language :: Python :: 3.10
Classifier: Programming Language :: Python :: 3.11
Classifier: Programming Language :: Python :: 3.12
Requires-Python: >=3.8
License-File: LICENSE
Requires-Dist: typer
Requires-Dist: loguru
Requires-Dist: pyyaml
Requires-Dist: schema
Requires-Dist: flask
Requires-Dist: flask-socketio
Requires-Dist: flask-login
Requires-Dist: simple-websocket
Requires-Dist: gevent
Requires-Dist: gevent-websocket
